companion/__init__.py
companion/utils.py
companion-0.0.2.dist-info/LICENSE
companion-0.0.2.dist-info/METADATA
companion-0.0.2.dist-info/WHEEL
companion-0.0.2.dist-info/top_level.txt
companion-0.0.2.dist-info/RECORD
