Metadata-Version: 2.1
Name: companion
Version: 0.0.2
Summary: Companion robot
Home-page: https://github.com/remakeai/kiddo
Author: Remake AI
Author-email: iliao@remake.ai
License: UNKNOWN
Platform: UNKNOWN
Classifier: Programming Language :: Python :: 3
Classifier: Development Status :: 1 - Planning
Classifier: License :: OSI Approved :: Apache Software License
Classifier: Operating System :: OS Independent
Requires-Python: >=3.5
